tuikit/__const__.py
tuikit/__init__.py
tuikit/__storage__.py
tuikit/_version.py
tuikit/astools.py
tuikit/console.py
tuikit/exceptions.py
tuikit/listools.py
tuikit/logictools.py
tuikit/textools.py
tuikit/timetools.py
tuikit/zonetools.py
tuikit/tzdata/Africa.json
tuikit/tzdata/America.json
tuikit/tzdata/Asia.json
tuikit/tzdata/Australia.json
tuikit/tzdata/Europe.json
tuikit/tzdata/Pacific.json
tuikit/tzdata/aliases.json
tuikit-1.0.0.dist-info/licenses/LICENSE
tuikit-1.0.0.dist-info/METADATA
tuikit-1.0.0.dist-info/WHEEL
tuikit-1.0.0.dist-info/top_level.txt
tuikit-1.0.0.dist-info/RECORD
