Metadata-Version: 2.4
Name: tuikit
Version: 1.0.0
Summary: Lightweight TUI utilities: console, text, lists, timezones and logic helpers.
Author: Caleb M. Sibanda
Author-email: darkian.dev@gmail.com
License: MIT
Project-URL: Homepage, https://github.com/2kDarki
Project-URL: Repository, https://github.com/2kDarki/TUI-Toolkit
Project-URL: Issues, https://github.com/2kDarki/TUI-Toolkit/issues
Keywords: tui,cui,console,timezone,utilities,toolkit
Classifier: Programming Language :: Python :: 3
Classifier: Programming Language :: Python :: 3 :: Only
Classifier: License :: OSI Approved :: MIT License
Classifier: Operating System :: OS Independent
Classifier: Intended Audience :: Developers
Classifier: Topic :: Software Development :: Libraries
Requires-Python: >=3.10
License-File: LICENSE
Dynamic: author
Dynamic: author-email
Dynamic: license-file
